cs/__init__.py
cs/tools/__init__.py
cs/tools/cs_api_tool.py
cs/tools/utils.py
cs/yamls/cs__api_tool.yaml
tests/__init__.py
tests/test_cs_api_tool.py
cs_intelligence_flow-0.0.3.dist-info/METADATA
cs_intelligence_flow-0.0.3.dist-info/WHEEL
cs_intelligence_flow-0.0.3.dist-info/entry_points.txt
cs_intelligence_flow-0.0.3.dist-info/top_level.txt
cs_intelligence_flow-0.0.3.dist-info/RECORD
