Metadata-Version: 2.1
Name: cs_intelligence_flow
Version: 0.0.3
Summary: This is CS Intelligence prompt flow
